README.md
gmswitch/__init__.py
gmswitch/generate.py
gmswitch/measures.py
gmswitch/switch.py
images/output.png
images/partition1.png
images/partition2.png
images/partition3.png
images/switch1.png
images/switch2.png
images/switch3.png
gmswitch-1.0.2.dist-info/LICENSE.txt
gmswitch-1.0.2.dist-info/METADATA
gmswitch-1.0.2.dist-info/WHEEL
gmswitch-1.0.2.dist-info/RECORD
