Metadata-Version: 2.1
Name: gmswitch
Version: 1.0.2
Summary: A library that performs Godsil-McKay switching on graphs.
License: MIT
Author: Ahmet Erdem
Author-email: ahmetblk1035@gmail.com
Requires-Python: >=3.10
Classifier: License :: OSI Approved :: MIT License
Classifier: Programming Language :: Python :: 3
Classifier: Programming Language :: Python :: 3.10
Classifier: Programming Language :: Python :: 3.11
Classifier: Programming Language :: Python :: 3.12
Classifier: Programming Language :: Python :: 3.13
Requires-Dist: networkx (>=3.0)
Requires-Dist: numpy (>=1.23)
